[{"employeeId":"4060741400333864216","email":"Vladyslav_Kutsenko@epam.com","firstName":"Vladyslav","lastName":"Kutsenko","location":"CIS, Ukraine, Kharkiv, 23 Serpnya str., 33g, 1st floor, 105","primarySkill":{"id":"4060741400007923323","name":"JavaScript"},"title":"Student","hireDate":"13-Mar-2018","unit":{"id":"4060741400008848514","name":".NET & Front-End Lab, Kharkiv"},"manager":{"id":"4060741400007844073","firstName":"Evgeniy","lastName":"Khramtsov"},"photoUrl":"https://static.cdn.epam.com/avatar/76b20bddff3e396cbd164fa5c322d071.jpg"},{"employeeId":"4060741400333850704","email":"Anastasia_Hahanova@epam.com","firstName":"Anastasia","lastName":"Hahanova","location":"CIS, Ukraine, Kharkiv, 23 Serpnya str., 33g, 1st floor, 105","primarySkill":{"id":"4060741400007923323","name":"JavaScript"},"title":"Student","hireDate":"13-Mar-2018","unit":{"id":"4060741400008848514","name":".NET & Front-End Lab, Kharkiv"},"manager":{"id":"4060741400007844073","firstName":"Evgeniy","lastName":"Khramtsov"},"photoUrl":"https://static.cdn.epam.com/avatar/3e9b8d156dee937f1fd0d40b45be7fdd.jpg"},{"employeeId":"4060741400333836739","email":"Yulia_Cherepakhina@epam.com","firstName":"Yulia","lastName":"Cherepakhina","location":"CIS, Ukraine, Kharkiv, 23 Serpnya str., 33g, 1st floor, 105","primarySkill":{"id":"4060741400007923323","name":"JavaScript"},"title":"Student","hireDate":"13-Mar-2018","unit":{"id":"4060741400008848514","name":".NET & Front-End Lab, Kharkiv"},"manager":{"id":"4060741400007844073","firstName":"Evgeniy","lastName":"Khramtsov"},"photoUrl":"https://static.cdn.epam.com/avatar/c8aea20920ecc6faea2227d856dbf30a.jpg"},{"employeeId":"4060741400333851104","email":"Andrii_Chernukha1@epam.com","firstName":"Andrii","lastName":"Chernukha1","location":"CIS, Ukraine, Kharkiv, 23 Serpnya str., 33g, 1st floor, 105","primarySkill":{"id":"4060741400007923323","name":"JavaScript"},"title":"Student","hireDate":"13-Mar-2018","unit":{"id":"4060741400008848514","name":".NET & Front-End Lab, Kharkiv"},"manager":{"id":"4060741400007844073","firstName":"Evgeniy","lastName":"Khramtsov"},"photoUrl":"https://static.cdn.epam.com/avatar/a79549804c370413ac5ffc446745a5d1.jpg"},{"employeeId":"4060741400333837285","email":"Oleksandr_Yehorov@epam.com","firstName":"Oleksandr","lastName":"Yehorov","location":"CIS, Ukraine, Kharkiv, 23 Serpnya str., 33g, 1st floor, 105","primarySkill":{"id":"4060741400007923323","name":"JavaScript"},"title":"Student","hireDate":"13-Mar-2018","unit":{"id":"4060741400008848514","name":".NET & Front-End Lab, Kharkiv"},"manager":{"id":"4060741400007844073","firstName":"Evgeniy","lastName":"Khramtsov"},"photoUrl":"https://static.cdn.epam.com/avatar/9d44be906744e2b2fdd268b25071beca.jpg"},{"employeeId":"4060741400333860579","email":"Maksym_Dryha@epam.com","firstName":"Maksym","lastName":"Dryha","location":"CIS, Ukraine, Kharkiv, 23 Serpnya str., 33g, 1st floor, 105","primarySkill":{"id":"4060741400007923323","name":"JavaScript"},"title":"Student","hireDate":"13-Mar-2018","unit":{"id":"4060741400008848514","name":".NET & Front-End Lab, Kharkiv"},"manager":{"id":"4060741400007844073","firstName":"Evgeniy","lastName":"Khramtsov"},"photoUrl":"https://static.cdn.epam.com/avatar/91ba298dff7cc95aeb29382b6aa042a5.jpg"},{"employeeId":"4060741400334285885","email":"Artem_Yasenko@epam.com","firstName":"Artem","lastName":"Yasenko","location":"CIS, Ukraine, Kharkiv, 23 Serpnya str., 33g, 1st floor, 105","primarySkill":{"id":"4060741400007923323","name":"JavaScript"},"title":"Student","hireDate":"14-Mar-2018","unit":{"id":"4060741400008848514","name":".NET & Front-End Lab, Kharkiv"},"manager":{"id":"4060741400007844073","firstName":"Evgeniy","lastName":"Khramtsov"},"photoUrl":"https://static.cdn.epam.com/avatar/d9a426dbf7e3f28223be335660bd29d2.jpg"},{"employeeId":"4060741400333851115","email":"Oleksandr_Antonenko@epam.com","firstName":"Oleksandr","lastName":"Antonenko","location":"CIS, Ukraine, Kharkiv, 23 Serpnya str., 33g, 1st floor, 105","primarySkill":{"id":"4060741400007923323","name":"JavaScript"},"title":"Student","hireDate":"13-Mar-2018","unit":{"id":"4060741400008848514","name":".NET & Front-End Lab, Kharkiv"},"manager":{"id":"4060741400007844073","firstName":"Evgeniy","lastName":"Khramtsov"},"photoUrl":"https://static.cdn.epam.com/avatar/5efd64a86d4c35064748b2eb7ccda38e.jpg"},{"employeeId":"4060741400333863835","email":"Tetiana_Krasiuk@epam.com","firstName":"Tetiana","lastName":"Krasiuk","location":"CIS, Ukraine, Kharkiv, 23 Serpnya str., 33g, 1st floor, 105","primarySkill":{"id":"4060741400007923323","name":"JavaScript"},"title":"Student","hireDate":"13-Mar-2018","unit":{"id":"4060741400008848514","name":".NET & Front-End Lab, Kharkiv"},"manager":{"id":"4060741400007844073","firstName":"Evgeniy","lastName":"Khramtsov"},"photoUrl":"https://static.cdn.epam.com/avatar/57279b7a000131949e53a795a05323d5.jpg"},{"employeeId":"4060741400333863847","email":"Volodymyr_Lehenkyi@epam.com","firstName":"Volodymyr","lastName":"Lehenkyi","location":"CIS, Ukraine, Kharkiv, 23 Serpnya str., 33g, 1st floor, 105","primarySkill":{"id":"4060741400007923323","name":"JavaScript"},"title":"Student","hireDate":"13-Mar-2018","unit":{"id":"4060741400008848514","name":".NET & Front-End Lab, Kharkiv"},"manager":{"id":"4060741400007844073","firstName":"Evgeniy","lastName":"Khramtsov"},"photoUrl":"https://static.cdn.epam.com/avatar/35a79364a18e772299cb60cea5fc5987.jpg"},{"employeeId":"4060741400333860561","email":"Anastasiia_Patralova@epam.com","firstName":"Anastasiia","lastName":"Patralova","location":"CIS, Ukraine, Kharkiv, 23 Serpnya str., 33g, 1st floor, 105","primarySkill":{"id":"4060741400007923323","name":"JavaScript"},"title":"Student","hireDate":"13-Mar-2018","unit":{"id":"4060741400008848514","name":".NET & Front-End Lab, Kharkiv"},"manager":{"id":"4060741400007844073","firstName":"Evgeniy","lastName":"Khramtsov"},"photoUrl":"https://static.cdn.epam.com/avatar/7b33b08088c47f10fa873b31a993124d.jpg"},{"employeeId":"4060741400333850717","email":"Anzhelika_Kachur@epam.com","firstName":"Anzhelika","lastName":"Kachur","location":"CIS, Ukraine, Kharkiv, 23 Serpnya str., 33g, 1st floor, 105","primarySkill":{"id":"4060741400007923323","name":"JavaScript"},"title":"Student","hireDate":"13-Mar-2018","unit":{"id":"4060741400008848514","name":".NET & Front-End Lab, Kharkiv"},"manager":{"id":"4060741400007844073","firstName":"Evgeniy","lastName":"Khramtsov"},"photoUrl":"https://static.cdn.epam.com/avatar/2dcae775300dcadda88efae9250b4fd3.jpg"}]